{
  "1-rdn-amanat-1042": {
    "bytesIn": 544732,
    "bytesOut": 2030146,
    "uptime": "2h24m35s"
  },
  "1-rdn-3": {
    "bytesIn": 76999369,
    "bytesOut": 212135385,
    "uptime": "2h24m34s"
  },
  "0-rdn-amanat-1042": {
    "bytesIn": 102149779,
    "bytesOut": 2210636715,
    "uptime": "1h23m35s"
  },
  "0-rdn-3": {
    "bytesIn": 393920530,
    "bytesOut": 6113300831,
    "uptime": "6h15m8s"
  },
  "2-rdn-mojib-1005": {
    "bytesIn": 358100182,
    "bytesOut": 5958467977,
    "uptime": "3h55m51s"
  },
  "2-rdn-college-1001": {
    "bytesIn": 158266048,
    "bytesOut": 3142830556,
    "uptime": "2h50m34s"
  },
  "2-rdn-college-1003": {
    "bytesIn": 713934,
    "bytesOut": 478170,
    "uptime": "3h57m41s"
  },
  "2-rdn-muslim-1002": {
    "bytesIn": 44344399,
    "bytesOut": 1234418409,
    "uptime": "3h57m26s"
  },
  "2-rdn-notun-1004": {
    "bytesIn": 80714470,
    "bytesOut": 1501608894,
    "uptime": "3h57m26s"
  },
  "2-rdn-notun-1008": {
    "bytesIn": 90326195,
    "bytesOut": 1288781024,
    "uptime": "3h57m22s"
  },
  "2-rdn-amanat-1019": {
    "bytesIn": 264180450,
    "bytesOut": 5471238067,
    "uptime": "6h19m32s"
  },
  "2-rdn-amanat-1009": {
    "bytesIn": 52394986,
    "bytesOut": 2012993103,
    "uptime": "3h57m23s"
  },
  "2-rdn-amanat-1031": {
    "bytesIn": 80580,
    "bytesOut": 79776,
    "uptime": "3h57m21s"
  },
  "2-rdn-akdewan-1003": {
    "bytesIn": 94677218,
    "bytesOut": 1439288366,
    "uptime": "3h55m52s"
  },
  "2-rdn-muslim-1010": {
    "bytesIn": 73840031,
    "bytesOut": 1909055737,
    "uptime": "3h56m48s"
  },
  "2-rdn-amanat-1037": {
    "bytesIn": 633399222,
    "bytesOut": 3962890035,
    "uptime": "3h56m44s"
  },
  "2-rdn-awlia-1003": {
    "bytesIn": 219912047,
    "bytesOut": 5365686711,
    "uptime": "3h56m39s"
  },
  "2-rdn-muslim-1012": {
    "bytesIn": 18869408,
    "bytesOut": 244990869,
    "uptime": "3h43m"
  },
  "2-rdn-rajmoni-1003": {
    "bytesIn": 22001014,
    "bytesOut": 407687736,
    "uptime": "3h56m39s"
  },
  "2-rdn-rajmoni-1002": {
    "bytesIn": 1042703,
    "bytesOut": 1466069,
    "uptime": "3h56m7s"
  },
  "2-rdn-cof-1001": {
    "bytesIn": 893809184,
    "bytesOut": 13150976037,
    "uptime": "3h56m6s"
  },
  "2-rdn-amanat-1032": {
    "bytesIn": 644886650,
    "bytesOut": 1856536842,
    "uptime": "3h56m4s"
  },
  "2-rdn-awlia-1004": {
    "bytesIn": 67282672,
    "bytesOut": 1133492245,
    "uptime": "3h56m4s"
  },
  "2-rdn-amanat-1008": {
    "bytesIn": 189506218,
    "bytesOut": 4150326724,
    "uptime": "2h17m56s"
  },
  "2-rdn-mortel-1007": {
    "bytesIn": 211994312,
    "bytesOut": 2035151575,
    "uptime": "3h56m5s"
  },
  "2-rdn-college-1002": {
    "bytesIn": 56468470,
    "bytesOut": 385908622,
    "uptime": "39m51s"
  },
  "2-rdn-mortel-1011": {
    "bytesIn": 737134148,
    "bytesOut": 4579491656,
    "uptime": "3h52m8s"
  },
  "2-rdn-muslim-1001": {
    "bytesIn": 298804417,
    "bytesOut": 4733217095,
    "uptime": "3h55m55s"
  },
  "2-rdn-mortel-1009": {
    "bytesIn": 152550834,
    "bytesOut": 7167173955,
    "uptime": "3h56m5s"
  },
  "2-rdn-debasis-1001": {
    "bytesIn": 7399488,
    "bytesOut": 320577430,
    "uptime": "3h56m6s"
  },
  "2-rdn-amanat-1027": {
    "bytesIn": 681830093,
    "bytesOut": 8520447266,
    "uptime": "3h55m46s"
  },
  "2-rdn-motel-1005": {
    "bytesIn": 340798723,
    "bytesOut": 2710349827,
    "uptime": "3h55m46s"
  },
  "2-rdn-amanat-1005": {
    "bytesIn": 278543146,
    "bytesOut": 7836969293,
    "uptime": "3h55m46s"
  },
  "2-rdn-mojib-1011": {
    "bytesIn": 485374546,
    "bytesOut": 5927620535,
    "uptime": "3h56m3s"
  },
  "2-rdn-mortel-1012": {
    "bytesIn": 68663613,
    "bytesOut": 1148526643,
    "uptime": "3h56m4s"
  },
  "2-rdn-mojib-1004": {
    "bytesIn": 193592663,
    "bytesOut": 4135646042,
    "uptime": "3h54m53s"
  },
  "2-rdn-cof-1010": {
    "bytesIn": 198053773,
    "bytesOut": 1827554756,
    "uptime": "3h54m19s"
  },
  "2-rdn-amanat-1013": {
    "bytesIn": 442656453,
    "bytesOut": 10064939785,
    "uptime": "3h56m3s"
  },
  "2-rdn-notun-1001": {
    "bytesIn": 46157282,
    "bytesOut": 1528725528,
    "uptime": "3h48m19s"
  },
  "2-rdn-amanat-1035": {
    "bytesIn": 149365534,
    "bytesOut": 3620345688,
    "uptime": "3h48m19s"
  },
  "2-rdn-notun-1002": {
    "bytesIn": 338162529,
    "bytesOut": 7804618154,
    "uptime": "3h48m15s"
  },
  "2-rdn-mojib-1009": {
    "bytesIn": 79472753,
    "bytesOut": 2631150594,
    "uptime": "3h55m52s"
  },
  "2-rdn-muslim-1008": {
    "bytesIn": 125425524,
    "bytesOut": 3287862286,
    "uptime": "3h56m48s"
  },
  "2-rdn-mojib-1008": {
    "bytesIn": 50200743,
    "bytesOut": 1336813245,
    "uptime": "3h56m4s"
  },
  "2-rdn-amanat-1041": {
    "bytesIn": 2585427535,
    "bytesOut": 13959271931,
    "uptime": "18h4m52s"
  },
  "2-rdn-rajmoni-1001": {
    "bytesIn": 3557165427,
    "bytesOut": 42489775967,
    "uptime": "1d13h27m39s"
  },
  "2-test": {
    "bytesIn": 0,
    "bytesOut": 0,
    "uptime": "13h46m59s"
  },
  "2-rdn-mojib-1006": {
    "bytesIn": 184981210,
    "bytesOut": 3957914239,
    "uptime": "3h56m49s"
  },
  "2-rdn-1": {
    "bytesIn": 392108576,
    "bytesOut": 6354797497,
    "uptime": "3h56m46s"
  },
  "2-rdn-muslim-1017": {
    "bytesIn": 1053353168,
    "bytesOut": 10212254865,
    "uptime": "17h13m36s"
  },
  "2-rdn-muslim-1014": {
    "bytesIn": 232594348,
    "bytesOut": 5896237182,
    "uptime": "3h57m24s"
  },
  "2-rdn-amanat-1011": {
    "bytesIn": 38577882,
    "bytesOut": 1150127995,
    "uptime": "3h56m51s"
  },
  "2-rdn-amanat-1012": {
    "bytesIn": 172108707,
    "bytesOut": 3254599825,
    "uptime": "3h57m21s"
  },
  "2-rdn-amanat-1029": {
    "bytesIn": 523824268,
    "bytesOut": 1638634181,
    "uptime": "3h56m50s"
  },
  "2-rdn-rajmoni-1006": {
    "bytesIn": 6240489,
    "bytesOut": 102308909,
    "uptime": "3h56m51s"
  },
  "2-rdn-rajmoni-1008": {
    "bytesIn": 16792956,
    "bytesOut": 544320393,
    "uptime": "3h56m47s"
  },
  "2-rdn-amanat-1020": {
    "bytesIn": 31106550,
    "bytesOut": 402894458,
    "uptime": "3h56m50s"
  },
  "2-rdn-muslim-1016": {
    "bytesIn": 158469638,
    "bytesOut": 4536900524,
    "uptime": "3h56m49s"
  },
  "2-rdn-amanat-1007": {
    "bytesIn": 78735295,
    "bytesOut": 1671207821,
    "uptime": "3h56m49s"
  },
  "2-rdn-mojib-1010": {
    "bytesIn": 334970241,
    "bytesOut": 5298270617,
    "uptime": "3h56m1s"
  },
  "2-rdn-muslim-1015": {
    "bytesIn": 181485045,
    "bytesOut": 1291992554,
    "uptime": "3h57m24s"
  },
  "2-rdn-amanat-1047": {
    "bytesIn": 46338855,
    "bytesOut": 775905386,
    "uptime": "3h56m49s"
  },
  "2-rdn-rajmoni-1010": {
    "bytesIn": 152152980,
    "bytesOut": 2541960695,
    "uptime": "3h55m55s"
  },
  "2-rdn-amanat-1004": {
    "bytesIn": 121178863,
    "bytesOut": 3695240453,
    "uptime": "6h19m21s"
  },
  "2-rdn-amanat-1024": {
    "bytesIn": 240508440,
    "bytesOut": 2777460726,
    "uptime": "3h56m43s"
  },
  "2-rdn-amanat-1038": {
    "bytesIn": 78396751,
    "bytesOut": 726958672,
    "uptime": "3h56m39s"
  },
  "2-rdn-akdewan-1001": {
    "bytesIn": 61812065,
    "bytesOut": 884256379,
    "uptime": "2h17m11s"
  },
  "2-rdn-mojib-1012": {
    "bytesIn": 459796860,
    "bytesOut": 9362965378,
    "uptime": "3h56m39s"
  },
  "2-rdn-amanat-1025": {
    "bytesIn": 935824913,
    "bytesOut": 7100198589,
    "uptime": "3h56m7s"
  },
  "2-rdn-notun-1012": {
    "bytesIn": 91434515,
    "bytesOut": 3356300655,
    "uptime": "3h56m4s"
  },
  "2-rdn-notun-1016": {
    "bytesIn": 324434615,
    "bytesOut": 11502029932,
    "uptime": "10h52m3s"
  },
  "2-rdn-mojib-1002": {
    "bytesIn": 110932478,
    "bytesOut": 3579501406,
    "uptime": "3h56m7s"
  },
  "2-rdn-akdewan-1004": {
    "bytesIn": 40989477,
    "bytesOut": 978002274,
    "uptime": "3h55m56s"
  },
  "2-rdn-amanat-1018": {
    "bytesIn": 66504419,
    "bytesOut": 1547026479,
    "uptime": "2h17m48s"
  },
  "2-rdn-amanat-1028": {
    "bytesIn": 330826007,
    "bytesOut": 6490198229,
    "uptime": "3h56m44s"
  },
  "2-rdn-tnt-1001": {
    "bytesIn": 11775917,
    "bytesOut": 539984878,
    "uptime": "55m36s"
  },
  "2-rdn-montri-1006": {
    "bytesIn": 66895128,
    "bytesOut": 762216759,
    "uptime": "3h56m8s"
  },
  "2-rdn-mojib-1001": {
    "bytesIn": 263680033,
    "bytesOut": 5117215178,
    "uptime": "3h55m8s"
  },
  "2-rdn-college-1006": {
    "bytesIn": 213995514,
    "bytesOut": 5649495125,
    "uptime": "3h55m7s"
  },
  "2-rdn-3": {
    "bytesIn": 625875971,
    "bytesOut": 9174932238,
    "uptime": "3h55m53s"
  },
  "2-rdn-amanat-1003": {
    "bytesIn": 210946179,
    "bytesOut": 1019591969,
    "uptime": "3h55m3s"
  },
  "2-rdn-notun-1014": {
    "bytesIn": 56600759,
    "bytesOut": 1596864362,
    "uptime": "3h54m48s"
  },
  "2-rdn-amanat-1033": {
    "bytesIn": 94444081,
    "bytesOut": 3143652723,
    "uptime": "2h50m40s"
  },
  "2-rdn-amanat-1015": {
    "bytesIn": 154242774,
    "bytesOut": 5441687203,
    "uptime": "3h57m24s"
  },
  "2-rdn-awlia-1005": {
    "bytesIn": 714206383,
    "bytesOut": 5884848068,
    "uptime": "3h30m28s"
  },
  "2-rdn-awlia-1001": {
    "bytesIn": 327296862,
    "bytesOut": 5342159437,
    "uptime": "3h55m9s"
  },
  "2-rdn-amanat-1039": {
    "bytesIn": 1219603621,
    "bytesOut": 2083720318,
    "uptime": "6h26m39s"
  },
  "2-rdn-sonaton-1004": {
    "bytesIn": 11319515,
    "bytesOut": 178095809,
    "uptime": "3h48m22s"
  },
  "2-rdn-notun-1009": {
    "bytesIn": 410625107,
    "bytesOut": 6143030553,
    "uptime": "3h48m10s"
  },
  "2-rdn-notun-1005": {
    "bytesIn": 67490911,
    "bytesOut": 3591987540,
    "uptime": "3h48m14s"
  },
  "2-rdn-notun-1010": {
    "bytesIn": 196582829,
    "bytesOut": 5659480246,
    "uptime": "3h48m11s"
  },
  "2-rdn-sonaton-1005": {
    "bytesIn": 90203555,
    "bytesOut": 2262972086,
    "uptime": "5h34m35s"
  },
  "2-rdn-sonaton-1001": {
    "bytesIn": 207522445,
    "bytesOut": 4742278653,
    "uptime": "3h47m53s"
  },
  "2-rdn-notun-1013": {
    "bytesIn": 373685531,
    "bytesOut": 514872825,
    "uptime": "3h47m40s"
  },
  "2-rdn-muslim-1021": {
    "bytesIn": 122465682,
    "bytesOut": 2500214620,
    "uptime": "5d11h34m51s"
  },
  "2-rdn-office": {
    "bytesIn": 706,
    "bytesOut": 1287,
    "uptime": "15s"
  },
  "2-rdn-amanat-1065": {
    "bytesIn": 6266084955,
    "bytesOut": 185620216867,
    "uptime": "3d17h58m38s"
  },
  "2-rdn-amanat-1050": {
    "bytesIn": 4690817508,
    "bytesOut": 76734594726,
    "uptime": "3d18h30m23s"
  },
  "2-rdn-montri-1007": {
    "bytesIn": 170050591,
    "bytesOut": 7520048522,
    "uptime": "17h32m19s"
  },
  "2-rdn-montri-1003": {
    "bytesIn": 65507411,
    "bytesOut": 1049900968,
    "uptime": "3h56m46s"
  },
  "2-rdn-notun-1020": {
    "bytesIn": 445878280,
    "bytesOut": 5803125948,
    "uptime": "3h57m24s"
  },
  "2-rdn-muslim-1007": {
    "bytesIn": 364644063,
    "bytesOut": 2800470845,
    "uptime": "3h57m22s"
  },
  "2-rdn-muslim-1023": {
    "bytesIn": 140564307,
    "bytesOut": 3478130499,
    "uptime": "3h57m22s"
  },
  "2-rdn-muslim-1020": {
    "bytesIn": 16882698,
    "bytesOut": 362831755,
    "uptime": "3h57m24s"
  },
  "2-rdn-muslim-1019": {
    "bytesIn": 1370677116,
    "bytesOut": 6512545253,
    "uptime": "3h57m23s"
  },
  "2-rdn-amanat-1061": {
    "bytesIn": 118977051,
    "bytesOut": 3464601754,
    "uptime": "3h5m47s"
  },
  "2-rdn-muslim-1022": {
    "bytesIn": 46974083,
    "bytesOut": 1104869982,
    "uptime": "3h57m22s"
  },
  "2-rdn-amanat-1060": {
    "bytesIn": 429448523,
    "bytesOut": 4816889136,
    "uptime": "3h56m47s"
  },
  "2-rdn-amanat-1067": {
    "bytesIn": 2737057676,
    "bytesOut": 1197520176,
    "uptime": "3h57m51s"
  },
  "2-rdn-muslim-1027": {
    "bytesIn": 36395614,
    "bytesOut": 800750538,
    "uptime": "3h56m50s"
  },
  "2-rdn-motel-1025": {
    "bytesIn": 683665850,
    "bytesOut": 11322687540,
    "uptime": "3h56m49s"
  },
  "2-rdn-amanat-1052": {
    "bytesIn": 248542763,
    "bytesOut": 4141534511,
    "uptime": "3h56m50s"
  },
  "2-rdn-notun-1019": {
    "bytesIn": 34067643,
    "bytesOut": 999465399,
    "uptime": "3h56m49s"
  },
  "2-rdn-amanat-1059": {
    "bytesIn": 21636748,
    "bytesOut": 743047283,
    "uptime": "3h56m48s"
  },
  "2-rdn-amanat-1051": {
    "bytesIn": 189096299,
    "bytesOut": 4739576574,
    "uptime": "3h56m48s"
  },
  "2-rdn-mojib-1017": {
    "bytesIn": 297544293,
    "bytesOut": 6016170813,
    "uptime": "3h56m41s"
  },
  "2-rdn-muslim-1004": {
    "bytesIn": 72626377,
    "bytesOut": 461492999,
    "uptime": "3h56m42s"
  },
  "2-rdn-amanat-1058": {
    "bytesIn": 102571170,
    "bytesOut": 1794049396,
    "uptime": "3h56m6s"
  },
  "2-rdn-rajmoni-1013": {
    "bytesIn": 2001704219,
    "bytesOut": 26723287409,
    "uptime": "18h55m6s"
  },
  "2-rdn-amanat-1068": {
    "bytesIn": 139022205,
    "bytesOut": 3278445029,
    "uptime": "3h55m59s"
  },
  "2-rdn-motel-1019": {
    "bytesIn": 620331418,
    "bytesOut": 16791917076,
    "uptime": "3h56m8s"
  },
  "2-rdn-awlia-1006": {
    "bytesIn": 173890222,
    "bytesOut": 4612604789,
    "uptime": "3h55m52s"
  },
  "2-rdn-montri-1008": {
    "bytesIn": 841742480,
    "bytesOut": 1456819893,
    "uptime": "3h54m45s"
  },
  "2-rdn-motel-1018": {
    "bytesIn": 215081436,
    "bytesOut": 2525215799,
    "uptime": "3h55m46s"
  },
  "2-rdn-amanat-1054": {
    "bytesIn": 225635384,
    "bytesOut": 8020258047,
    "uptime": "3h55m11s"
  },
  "2-rdn-awlia-1009": {
    "bytesIn": 138632709,
    "bytesOut": 2292888773,
    "uptime": "3h55m58s"
  },
  "2-rdn-mojib-1016": {
    "bytesIn": 354974360,
    "bytesOut": 7560892465,
    "uptime": "3h55m10s"
  },
  "2-rdn-mojib-1014": {
    "bytesIn": 519384783,
    "bytesOut": 3418325737,
    "uptime": "3h55m42s"
  },
  "2-rdn-motel-1016": {
    "bytesIn": 3194204,
    "bytesOut": 10948251,
    "uptime": "3h56m42s"
  },
  "2-rdn-awlia-1002": {
    "bytesIn": 26177400,
    "bytesOut": 1086949813,
    "uptime": "3h55m50s"
  },
  "2-rdn-amanat-1014": {
    "bytesIn": 370864373,
    "bytesOut": 5254598926,
    "uptime": "3h54m43s"
  },
  "2-rdn-amanat-1062": {
    "bytesIn": 20432026,
    "bytesOut": 327464305,
    "uptime": "3h57m22s"
  },
  "2-rdn-motel-1015": {
    "bytesIn": 37994259,
    "bytesOut": 1064429489,
    "uptime": "3h56m6s"
  },
  "2-rdn-amanat-1063": {
    "bytesIn": 152768165,
    "bytesOut": 4279232668,
    "uptime": "3h55m47s"
  },
  "2-rdn-muslim-1025": {
    "bytesIn": 49079626,
    "bytesOut": 1100349007,
    "uptime": "3h56m42s"
  },
  "2-rdn-amanat-1056": {
    "bytesIn": 263383450,
    "bytesOut": 4235338000,
    "uptime": "3h49m8s"
  },
  "2-rdn-notun-1017": {
    "bytesIn": 235154844,
    "bytesOut": 4417803041,
    "uptime": "3h47m16s"
  },
  "2-rdn-sonaton-1008": {
    "bytesIn": 25501576,
    "bytesOut": 480071704,
    "uptime": "3h48m16s"
  },
  "2-rdn-notun-1018": {
    "bytesIn": 21063949,
    "bytesOut": 241053209,
    "uptime": "3h48m13s"
  },
  "2-rdn-sonaton-1007": {
    "bytesIn": 324418958,
    "bytesOut": 6491810941,
    "uptime": "3h48m12s"
  },
  "2-rdn-sonaton-1006": {
    "bytesIn": 443766630,
    "bytesOut": 2916784295,
    "uptime": "3h47m41s"
  },
  "2-rdn-college-1008": {
    "bytesIn": 6323507994,
    "bytesOut": 151044940242,
    "uptime": "1w2d11h59m55s"
  },
  "2-rdn-college-1012": {
    "bytesIn": 100071878,
    "bytesOut": 808715942,
    "uptime": "7h5m20s"
  },
  "2-rdn-college-1014": {
    "bytesIn": 1189339,
    "bytesOut": 1356293,
    "uptime": "3h57m29s"
  },
  "2-rdn-mojib-1007": {
    "bytesIn": 26632394,
    "bytesOut": 977638757,
    "uptime": "3h57m22s"
  },
  "2-rdn-motel-1023": {
    "bytesIn": 296323139,
    "bytesOut": 5385995035,
    "uptime": "3h57m22s"
  },
  "2-rdn-mojib-1018": {
    "bytesIn": 155895983,
    "bytesOut": 4030688779,
    "uptime": "3h57m21s"
  },
  "2-rdn-amanat-1021": {
    "bytesIn": 130027223,
    "bytesOut": 2156315816,
    "uptime": "3h56m50s"
  },
  "2-rdn-cof-1006": {
    "bytesIn": 247616145,
    "bytesOut": 4602585756,
    "uptime": "3h55m"
  },
  "2-rdn-amanat-1023": {
    "bytesIn": 227746012,
    "bytesOut": 4932600328,
    "uptime": "3h56m43s"
  },
  "2-rdn-amanat-1069": {
    "bytesIn": 101152081,
    "bytesOut": 2793489260,
    "uptime": "3h23m52s"
  },
  "2-rdn-mojib-1024": {
    "bytesIn": 4030252,
    "bytesOut": 118707,
    "uptime": "6h19m21s"
  },
  "2-rdn-akdewan-1006": {
    "bytesIn": 267345631,
    "bytesOut": 8052834851,
    "uptime": "3h55m56s"
  },
  "2-rdn-muslim-1031": {
    "bytesIn": 960255988,
    "bytesOut": 7839345423,
    "uptime": "3h56m41s"
  },
  "2-rdn-awlia-1011": {
    "bytesIn": 103550564,
    "bytesOut": 4551757986,
    "uptime": "3h55m52s"
  },
  "2-rdn-college-1013": {
    "bytesIn": 624828474,
    "bytesOut": 3393160113,
    "uptime": "3h56m44s"
  },
  "2-rdn-mojib-1023": {
    "bytesIn": 24252045,
    "bytesOut": 871192564,
    "uptime": "3h56m2s"
  },
  "2-rdn-mojib-1026": {
    "bytesIn": 4759098,
    "bytesOut": 182035023,
    "uptime": "3h56m2s"
  },
  "2-rdn-muslim-1011": {
    "bytesIn": 427978691,
    "bytesOut": 6857388067,
    "uptime": "3h56m43s"
  },
  "2-rdn-mojib-1021": {
    "bytesIn": 75658567,
    "bytesOut": 1383230419,
    "uptime": "3h56m40s"
  },
  "2-rdn-mojib-1025": {
    "bytesIn": 541806892,
    "bytesOut": 7377201904,
    "uptime": "3h55m51s"
  },
  "2-rdn-motel-1006": {
    "bytesIn": 461527427,
    "bytesOut": 4151265128,
    "uptime": "3h55m45s"
  },
  "2-rdn-college-1011": {
    "bytesIn": 10312297,
    "bytesOut": 4332328,
    "uptime": "3h55m43s"
  },
  "2-rdn-debasis-1002": {
    "bytesIn": 103537557,
    "bytesOut": 3327841465,
    "uptime": "3h55m12s"
  },
  "2-rdn-amanat-1030": {
    "bytesIn": 54390446,
    "bytesOut": 680059493,
    "uptime": "3h55m7s"
  },
  "2-rdn-amanat-1074": {
    "bytesIn": 612474004,
    "bytesOut": 4851605182,
    "uptime": "3h55m4s"
  },
  "2-rdn-mojib-1022": {
    "bytesIn": 180477752,
    "bytesOut": 4433059619,
    "uptime": "3h56m7s"
  },
  "2-rdn-montri-1011": {
    "bytesIn": 28571059,
    "bytesOut": 558239289,
    "uptime": "3h54m58s"
  },
  "2-rdn-amanat-1071": {
    "bytesIn": 33299862,
    "bytesOut": 607418429,
    "uptime": "3h56m2s"
  },
  "2-rdn-montri-1009": {
    "bytesIn": 78522628,
    "bytesOut": 1772956724,
    "uptime": "3h54m49s"
  },
  "2-rdn-amanat-1049": {
    "bytesIn": 179637459,
    "bytesOut": 3319481299,
    "uptime": "3h56m5s"
  },
  "2-rdn-mojib-1020": {
    "bytesIn": 40503181,
    "bytesOut": 459274003,
    "uptime": "2h17m11s"
  },
  "2-rdn-cof-1005": {
    "bytesIn": 15853783,
    "bytesOut": 249852217,
    "uptime": "3h55m47s"
  },
  "2-rdn-amanat-1034": {
    "bytesIn": 511323689,
    "bytesOut": 4707529599,
    "uptime": "3h56m43s"
  },
  "2-rdn-awlia-1012": {
    "bytesIn": 873796553,
    "bytesOut": 12596232463,
    "uptime": "3h56m40s"
  },
  "2-rdn-amanat-1070": {
    "bytesIn": 23611277,
    "bytesOut": 544412180,
    "uptime": "3h55m6s"
  },
  "2-rdn-college-1010": {
    "bytesIn": 3160538101,
    "bytesOut": 20252035730,
    "uptime": "4d13h11m"
  },
  "2-rdn-notun-1021": {
    "bytesIn": 59021768,
    "bytesOut": 1305064482,
    "uptime": "3h48m16s"
  },
  "2-rdn-amanat-1090": {
    "bytesIn": 2764212700,
    "bytesOut": 65685896986,
    "uptime": "2d20h10m4s"
  },
  "2-rdn-hospital-1002": {
    "bytesIn": 10355764446,
    "bytesOut": 47964620851,
    "uptime": "2d23h16m24s"
  },
  "2-rdn-amanat-1083": {
    "bytesIn": 265506007,
    "bytesOut": 4938111839,
    "uptime": "3h57m49s"
  },
  "2-rdn-awlia-1013": {
    "bytesIn": 156757390,
    "bytesOut": 3563376632,
    "uptime": "3h57m32s"
  },
  "2-rdn-vedvedi-1003": {
    "bytesIn": 54738427,
    "bytesOut": 132737649,
    "uptime": "3h57m23s"
  },
  "2-rdn-muslim-1032": {
    "bytesIn": 303277361,
    "bytesOut": 4282794157,
    "uptime": "3h57m24s"
  },
  "2-rdn-vedvedi-1002": {
    "bytesIn": 1768401,
    "bytesOut": 1085950,
    "uptime": "3h57m22s"
  },
  "2-rdn-notun-1011": {
    "bytesIn": 100709077,
    "bytesOut": 1761680339,
    "uptime": "3h57m21s"
  },
  "2-rdn-amanat-1081": {
    "bytesIn": 244732888,
    "bytesOut": 5106903332,
    "uptime": "3h56m49s"
  },
  "2-rdn-mojib-1028": {
    "bytesIn": 594388296,
    "bytesOut": 7811798632,
    "uptime": "3h57m22s"
  },
  "2-rdn-amanat-1084": {
    "bytesIn": 11720300,
    "bytesOut": 889932715,
    "uptime": "3h56m4s"
  },
  "2-rdn-muslim-1024": {
    "bytesIn": 158266494,
    "bytesOut": 3888728822,
    "uptime": "3h56m48s"
  },
  "2-rdn-amanat-1087": {
    "bytesIn": 89393831,
    "bytesOut": 2491322934,
    "uptime": "3h56m47s"
  },
  "2-rdn-shimul-1003": {
    "bytesIn": 137223609,
    "bytesOut": 2833118911,
    "uptime": "3h56m46s"
  },
  "2-rdn-shimul-1005": {
    "bytesIn": 7643865,
    "bytesOut": 1367973,
    "uptime": "2h58m12s"
  },
  "2-rdn-shimul-1004": {
    "bytesIn": 615177468,
    "bytesOut": 17937993647,
    "uptime": "18h25m38s"
  },
  "2-rdn-notun-1027": {
    "bytesIn": 80027899,
    "bytesOut": 3809521016,
    "uptime": "3h53m33s"
  },
  "2-rdn-shimul-1001": {
    "bytesIn": 95887582,
    "bytesOut": 2271020255,
    "uptime": "3h56m41s"
  },
  "2-rdn-vedvedi-1004": {
    "bytesIn": 65944003,
    "bytesOut": 2143049345,
    "uptime": "17h13m25s"
  },
  "2-rdn-notun-1006": {
    "bytesIn": 573934654,
    "bytesOut": 4438178505,
    "uptime": "3h30m8s"
  },
  "2-rdn-motel-1027": {
    "bytesIn": 85049693,
    "bytesOut": 2303298568,
    "uptime": "3h56m7s"
  },
  "2-rdn-amanat-1086": {
    "bytesIn": 1607655172,
    "bytesOut": 27758113318,
    "uptime": "3h56m40s"
  },
  "2-rdn-motel-1026": {
    "bytesIn": 68469648,
    "bytesOut": 71537023,
    "uptime": "3h55m52s"
  },
  "2-rdn-mojib-1029": {
    "bytesIn": 139342637,
    "bytesOut": 2841666967,
    "uptime": "3h55m52s"
  },
  "2-rdn-amanat-1076": {
    "bytesIn": 2593407381,
    "bytesOut": 44641888511,
    "uptime": "2d19m54s"
  },
  "2-rdn-amanat-1079": {
    "bytesIn": 109685569,
    "bytesOut": 3097228305,
    "uptime": "3h56m8s"
  },
  "2-rdn-vedvedi-1005": {
    "bytesIn": 225737205,
    "bytesOut": 6383099150,
    "uptime": "3h57m22s"
  },
  "2-rdn-motel-1009": {
    "bytesIn": 28785659,
    "bytesOut": 736512053,
    "uptime": "3h56m40s"
  },
  "2-rdn-debasis-1003": {
    "bytesIn": 190170897,
    "bytesOut": 5658569241,
    "uptime": "3h55m51s"
  },
  "2-rdn-akdewan-1005": {
    "bytesIn": 203320107,
    "bytesOut": 3527636512,
    "uptime": "3h56m8s"
  },
  "2-rdn-cof-1009": {
    "bytesIn": 228380337,
    "bytesOut": 1475542847,
    "uptime": "3h55m47s"
  },
  "2-rdn-amanat-1088": {
    "bytesIn": 432177490,
    "bytesOut": 7068607872,
    "uptime": "3h55m43s"
  },
  "2-rdn-motel-1003": {
    "bytesIn": 1541680,
    "bytesOut": 0,
    "uptime": "6h18m48s"
  },
  "2-rdn-awlia-1014": {
    "bytesIn": 101960497,
    "bytesOut": 2883794054,
    "uptime": "3h55m11s"
  },
  "2-rdn-amanat-1077": {
    "bytesIn": 454401536,
    "bytesOut": 4838510557,
    "uptime": "3h56m48s"
  },
  "2-rdn-cof-1008": {
    "bytesIn": 111159666,
    "bytesOut": 1356438375,
    "uptime": "3h54m58s"
  },
  "2-rdn-muslim-1033": {
    "bytesIn": 35337978,
    "bytesOut": 3081646092,
    "uptime": "3h54m43s"
  },
  "2-rdn-amanat-1091": {
    "bytesIn": 56450497,
    "bytesOut": 2820024028,
    "uptime": "2h16m14s"
  },
  "2-rdn-amanat-1089": {
    "bytesIn": 126739662,
    "bytesOut": 3857405130,
    "uptime": "3h57m23s"
  },
  "2-rdn-amanat-1078": {
    "bytesIn": 88822352,
    "bytesOut": 1295907233,
    "uptime": "3h57m22s"
  },
  "2-rdn-mojib-1027": {
    "bytesIn": 235248221,
    "bytesOut": 3205057754,
    "uptime": "3h55m59s"
  },
  "2-rdn-motel-1007": {
    "bytesIn": 15557722,
    "bytesOut": 332153081,
    "uptime": "3h55m50s"
  },
  "2-rdn-amanat-1055": {
    "bytesIn": 117820508,
    "bytesOut": 1713649956,
    "uptime": "3h57m24s"
  },
  "2-rdn-sonaton-1009": {
    "bytesIn": 16056,
    "bytesOut": 15180,
    "uptime": "44m39s"
  },
  "2-rdn-notun-1028": {
    "bytesIn": 368288338,
    "bytesOut": 10647755711,
    "uptime": "3h48m"
  },
  "2-rdn-sonaton-1011": {
    "bytesIn": 302210116,
    "bytesOut": 6473292919,
    "uptime": "16h21m43s"
  },
  "2-rdn-sonaton-1010": {
    "bytesIn": 697285559,
    "bytesOut": 8464523905,
    "uptime": "19h3m29s"
  },
  "2-rdn-kalin-1002": {
    "bytesIn": 41244,
    "bytesOut": 50852,
    "uptime": "5h13m34s"
  },
  "2-rdn-amanat-1100": {
    "bytesIn": 2635444284,
    "bytesOut": 29976046427,
    "uptime": "1d9h47m42s"
  },
  "2-rdn-amanat-1097": {
    "bytesIn": 128090909,
    "bytesOut": 2686376770,
    "uptime": "3h56m51s"
  },
  "2-rdn-amanat-1096": {
    "bytesIn": 320784702,
    "bytesOut": 7005425974,
    "uptime": "3h56m50s"
  },
  "2-rdn-amanat-1095": {
    "bytesIn": 136263946,
    "bytesOut": 2982164021,
    "uptime": "3h57m24s"
  },
  "2-rdn-amanat-1098": {
    "bytesIn": 52724869,
    "bytesOut": 1595525907,
    "uptime": "3h56m43s"
  },
  "2-rdn-sonaton-1013": {
    "bytesIn": 38158001,
    "bytesOut": 778144179,
    "uptime": "3h56m43s"
  },
  "2-rdn-amanat-1080": {
    "bytesIn": 117751939,
    "bytesOut": 1742032872,
    "uptime": "2h18m9s"
  },
  "2-rdn-muslim-1034": {
    "bytesIn": 137600896,
    "bytesOut": 1419179406,
    "uptime": "3h56m9s"
  },
  "2-rdn-awlia-1015": {
    "bytesIn": 176409849,
    "bytesOut": 2325963584,
    "uptime": "6h18m41s"
  },
  "2-rdn-amanat-1082": {
    "bytesIn": 63521693,
    "bytesOut": 1845098872,
    "uptime": "3h56m42s"
  },
  "2-rdn-amanat-1094": {
    "bytesIn": 36408290,
    "bytesOut": 913974497,
    "uptime": "2h5m46s"
  },
  "2-rdn-muslim-1026": {
    "bytesIn": 248622786,
    "bytesOut": 4124484188,
    "uptime": "3h51m38s"
  },
  "2-rdn-notun-1029": {
    "bytesIn": 298793098,
    "bytesOut": 1269930111,
    "uptime": "58m51s"
  },
  "2-rdn-amanat-1092": {
    "bytesIn": 6112319,
    "bytesOut": 248101403,
    "uptime": "3h20m33s"
  },
  "2-rdn-amanat-1099": {
    "bytesIn": 71983200,
    "bytesOut": 4114304050,
    "uptime": "3h56m42s"
  },
  "2-rdn-sonaton-1012": {
    "bytesIn": 4212925,
    "bytesOut": 59423003,
    "uptime": "37m57s"
  },
  "2-rdn-amanat-1017": {
    "bytesIn": 289513224,
    "bytesOut": 3727968938,
    "uptime": "9h27m35s"
  },
  "2-rdn-motel-1021": {
    "bytesIn": 431947773,
    "bytesOut": 8306890928,
    "uptime": "9h27m20s"
  },
  "2-rdn-kalin-1001": {
    "bytesIn": 663379925,
    "bytesOut": 4443538038,
    "uptime": "5h13m16s"
  },
  "2-rdn-muslim-1018": {
    "bytesIn": 7086795,
    "bytesOut": 187893589,
    "uptime": "59m31s"
  },
  "2-rdn-mortel-1002": {
    "bytesIn": 68040485,
    "bytesOut": 2859137084,
    "uptime": "6h31m35s"
  },
  "2-rdn-mojib-1015": {
    "bytesIn": 59892742,
    "bytesOut": 1989100270,
    "uptime": "3h55m11s"
  },
  "2-rdn-muslim-1028": {
    "bytesIn": 80444297,
    "bytesOut": 2359712977,
    "uptime": "3h41m34s"
  },
  "2-rdn-amanat-1002": {
    "bytesIn": 182289944,
    "bytesOut": 4249350905,
    "uptime": "2h18m37s"
  },
  "2-rdn-amanat-1046": {
    "bytesIn": 299029435,
    "bytesOut": 6267074179,
    "uptime": "3h55m44s"
  },
  "2-rdn-awlia-1007": {
    "bytesIn": 145947615,
    "bytesOut": 3618386656,
    "uptime": "3h55m43s"
  },
  "2-rdn-notun-1024": {
    "bytesIn": 905358918,
    "bytesOut": 20868075175,
    "uptime": "1d12h40m13s"
  },
  "2-rdn-shimul-1006": {
    "bytesIn": 30565748,
    "bytesOut": 815516757,
    "uptime": "3h55m8s"
  },
  "2-rdn-amanat-1073": {
    "bytesIn": 10138811,
    "bytesOut": 294062426,
    "uptime": "2h19m58s"
  },
  "2-rdn-rajmoni-1004": {
    "bytesIn": 19084,
    "bytesOut": 0,
    "uptime": "22m33s"
  },
  "2-rdn-rajmoni-1012": {
    "bytesIn": 262879589,
    "bytesOut": 6932755749,
    "uptime": "3h55m44s"
  },
  "2-rdn-amanat-1042": {
    "bytesIn": 454995048,
    "bytesOut": 13701320739,
    "uptime": "4h57m53s"
  },
  "2-rdn-muslim-1013": {
    "bytesIn": 381856952,
    "bytesOut": 2065966855,
    "uptime": "3h56m40s"
  },
  "0-rdn-1": {
    "bytesIn": 75761133,
    "bytesOut": 703972466,
    "uptime": "1h23m30s"
  },
  "3-rdn-amanat-1042": {
    "bytesIn": 150717515,
    "bytesOut": 3282857799,
    "uptime": "2h4m7s"
  },
  "3-rdn-1": {
    "bytesIn": 90739775,
    "bytesOut": 872886224,
    "uptime": "2h4m2s"
  },
  "3-rdn-mojib-1020": {
    "bytesIn": 92240014,
    "bytesOut": 1122665581,
    "uptime": "14h17m45s"
  },
  "0-rdn-mojib-1020": {
    "bytesIn": 92138053,
    "bytesOut": 1122528159,
    "uptime": "7h30m12s"
  },
  "2-rdn-akdewan-1002": {
    "bytesIn": 1012353648,
    "bytesOut": 18486132993,
    "uptime": "18h57m23s"
  },
  "2-rdn-college-1015": {
    "bytesIn": 191351,
    "bytesOut": 403727,
    "uptime": "3h57m23s"
  },
  "2-rdn-amanat-1006": {
    "bytesIn": 212485477,
    "bytesOut": 1606340169,
    "uptime": "3h57m21s"
  },
  "2-rdn-amanat-1022": {
    "bytesIn": 121599690,
    "bytesOut": 3760588138,
    "uptime": "3h56m50s"
  },
  "2-rdn-amanat-1101": {
    "bytesIn": 155426095,
    "bytesOut": 5474503286,
    "uptime": "3h56m47s"
  },
  "2-rdn-rajmoni-1011": {
    "bytesIn": 4449637,
    "bytesOut": 45483078,
    "uptime": "3h56m41s"
  },
  "2-rdn-mojib-1033": {
    "bytesIn": 35286187,
    "bytesOut": 935733498,
    "uptime": "3h55m56s"
  },
  "2-rdn-kalin-1003": {
    "bytesIn": 259683666,
    "bytesOut": 5765996837,
    "uptime": "5h12m47s"
  },
  "2-rdn-notun-1022": {
    "bytesIn": 4124,
    "bytesOut": 0,
    "uptime": "1m26s"
  },
  "2-rdn-amanat-1066": {
    "bytesIn": 74934697,
    "bytesOut": 2118160946,
    "uptime": "3h56m49s"
  },
  "2-rdn-mojib-1034": {
    "bytesIn": 41432727,
    "bytesOut": 1443261742,
    "uptime": "3h56m42s"
  },
  "2-rdn-kalin-1004": {
    "bytesIn": 225661794,
    "bytesOut": 4366151034,
    "uptime": "5h11m19s"
  },
  "2-rdn-awlia-1010": {
    "bytesIn": 137920867,
    "bytesOut": 4760488210,
    "uptime": "3h55m5s"
  }
}